wordcombinator/__init__.py
wordcombinator/main.py
wordcombinator-0.2.1.dist-info/METADATA
wordcombinator-0.2.1.dist-info/WHEEL
wordcombinator-0.2.1.dist-info/top_level.txt
wordcombinator-0.2.1.dist-info/RECORD
