Metadata-Version: 2.1
Name: wordcombinator
Version: 0.2.1
Home-page: https://github.com/SaishSaw
Author: saish
